flake8_dodgy/__init__.py
flake8_dodgy/flake8_dodgy.py
flake8_dodgy-0.0.1.dist-info/top_level.txt
flake8_dodgy-0.0.1.dist-info/entry_points.txt
flake8_dodgy-0.0.1.dist-info/METADATA
flake8_dodgy-0.0.1.dist-info/DESCRIPTION.rst
flake8_dodgy-0.0.1.dist-info/metadata.json
flake8_dodgy-0.0.1.dist-info/WHEEL
flake8_dodgy-0.0.1.dist-info/RECORD
