Metadata-Version: 2.0
Name: flake8-dodgy
Version: 0.0.1
Summary: UNKNOWN
Home-page: https://github.com/dbarbar/flake8_dodgy
Author: David Barbarisi
Author-email: davidbarbarisi@gmail.com
License: MIT
Keywords: flake8,dodgy
Platform: UNKNOWN
Classifier: Development Status :: 4 - Beta
Classifier: Environment :: Console
Classifier: Environment :: Plugins
Classifier: Intended Audience :: Developers
Classifier: License :: OSI Approved :: MIT License
Classifier: Natural Language :: English
Classifier: Operating System :: OS Independent
Classifier: Programming Language :: Python
Classifier: Programming Language :: Python :: 2
Classifier: Programming Language :: Python :: 2.7
Classifier: Programming Language :: Python :: 3
Classifier: Programming Language :: Python :: 3.5
Classifier: Topic :: Software Development :: Libraries :: Python Modules
Classifier: Topic :: Software Development :: Quality Assurance
Requires-Dist: flake8 (>=2.5.2,<3.0.0)
Requires-Dist: dodgy (>=0.1.9,<1.0.0)
Requires-Dist: setuptools
